{
  "name": "bug_scrub_csv_diff",
  "main": "__init__.py",
  "inputs": [
    {
      "description": "CSV of the Old Bug Scrub",
      "optional": false,
      "value": null,
      "type": "inputFile",
      "name": "old_filename"
    },
    {
      "description": "CSV of the New Bug Scrub",
      "optional": false,
      "value": null,
      "type": "inputFile",
      "name": "new_filename"
    }
  ],
  "author": "nimbhasi",
  "description": "This package accepts to CSVs, supposed to be created by another BDB script, bug_scrub_to_csv and finds the differences between the two.\nINPUT: Two files, old CSV, new CSV\nOUTPUT: records_added.csv, records_deleted.csv",
  "entitlements": [
    "public"
  ],
  "groups": [],
  "contributors": [],
  "minutes_saved": null,
  "labels": [],
  "service": "python3",
  "timeOut": 60000
}